df_strike_tut/__init__.py
df_strike_tut/df_main_tut.py
df_strike_tut/order_place.py
df_strike_tut-0.0.4.dist-info/LICENCE.txt
df_strike_tut-0.0.4.dist-info/METADATA
df_strike_tut-0.0.4.dist-info/WHEEL
df_strike_tut-0.0.4.dist-info/top_level.txt
df_strike_tut-0.0.4.dist-info/RECORD
