Metadata-Version: 2.1
Name: df-strike-tut
Version: 0.0.4
Summary: For generating A E S T H E T I C ascii art
Home-page: https://pypi.org/project/df-strike-tut/
Author: Denny Babu
Author-email: dannibabup@gmail.com
Classifier: Programming Language :: Python :: 3
Classifier: License :: OSI Approved :: MIT License
Classifier: Operating System :: OS Independent
Requires-Python: >=3.7
License-File: LICENCE.txt
